tfprovider/__init__.py
tfprovider/level1/__init__.py
tfprovider/level1/_async/__init__.py
tfprovider/level1/_async/rpc_plugin_server.py
tfprovider/level1/_common/__init__.py
tfprovider/level1/_common/rpc_plugin_server.py
tfprovider/level1/_sync/__init__.py
tfprovider/level1/_sync/rpc_plugin_server.py
tfprovider/level1/proto/grpc_controller.proto
tfprovider/level1/proto/tfplugin64.proto
tfprovider/level1/rpc_plugin.py
tfprovider/level2/__init__.py
tfprovider/level2/attribute_path.py
tfprovider/level2/diagnostics.py
tfprovider/level2/dynamic_value.py
tfprovider/level2/usable_schema.py
tfprovider/level2/wire_format.py
tfprovider/level2/wire_marshaling.py
tfprovider/level2/wire_representation.py
tfprovider/level3/__init__.py
tfprovider/level3/statically_typed_schema.py
tfprovider/level4/__init__.py
tfprovider/level4/_async/__init__.py
tfprovider/level4/_async/provider_servicer.py
tfprovider/level4/_sync/__init__.py
tfprovider/level4/_sync/provider_servicer.py
tfprovider/level4/async_provider_servicer.py
tfprovider/level4/provider_servicer.py
tfprovider/level4/utils.py
tfprovider/py.typed
tfprovider/tfprovider.png
tfprovider/tfprovider_level3.png
tfprovider-0.1.1.post1.dist-info/LICENSE
tfprovider-0.1.1.post1.dist-info/METADATA
tfprovider-0.1.1.post1.dist-info/WHEEL
tfprovider-0.1.1.post1.dist-info/RECORD
