Metadata-Version: 2.1
Name: tfprovider
Version: 0.1.1.post1
Summary: Implement Terraform providers in Python
Home-page: https://smheidrich.gitlab.io/tfprovider-python/
License: MPL-2.0
Author: smheidrich
Author-email: smheidrich@weltenfunktion.de
Requires-Python: >=3.11,<4.0
Classifier: License :: OSI Approved
Classifier: Programming Language :: Python :: 3
Classifier: Programming Language :: Python :: 3.11
Classifier: Programming Language :: Python :: 3.12
Requires-Dist: cryptography (>=41.0.4,<42.0.0)
Requires-Dist: grpcio (>=1.59.0,<2.0.0)
Requires-Dist: grpcio-health-checking (>=1.59.0,<2.0.0)
Requires-Dist: hc-go-plugin-server (>=0.1.0,<0.2.0)
Requires-Dist: msgpack (>=1.0.7,<2.0.0)
Requires-Dist: tfplugin-proto-all (>=0.1.0,<0.2.0)
Project-URL: Documentation, https://smheidrich.gitlab.io/tfprovider-python/
Project-URL: Repository, https://gitlab.com/smheidrich/tfprovider-python
